cytools/__init__.py
cytools/calabiyau.py
cytools/cone.py
cytools/config.py
cytools/polytope.py
cytools/polytopeface.py
cytools/toricvariety.py
cytools/triangulation.py
cytools/utils.py
cytools/h_polytope/__init__.py
cytools/h_polytope/h_polytope.py
cytools/helpers/basic_geometry.py
cytools/helpers/matrix.py
cytools/helpers/misc.py
cytools/ntfe/__init__.py
cytools/ntfe/face_triangulations.py
cytools/ntfe/ntfe.py
cytools/vector_config/__init__.py
cytools/vector_config/fan.py
cytools/vector_config/vectorconfiguration.py
cytools-1.4.5.dist-info/METADATA
cytools-1.4.5.dist-info/WHEEL
cytools-1.4.5.dist-info/licenses/LICENSE
cytools-1.4.5.dist-info/RECORD
