Metadata-Version: 2.4
Name: cytools
Version: 1.4.5
Summary: A software package for analyzing Calabi-Yau hypersurfaces in toric varieties.
Project-URL: Homepage, https://cy.tools
Project-URL: Documentation, https://cy.tools/docs/documentation/
Project-URL: Repository, https://github.com/LiamMcAllisterGroup/cytools
Author: Liam McAllister Group
License:                     GNU GENERAL PUBLIC LICENSE
License-File: LICENSE
Classifier: Development Status :: 5 - Production/Stable
Classifier: Intended Audience :: Science/Research
Classifier: License :: OSI Approved :: GNU General Public License v3 or later (GPLv3+)
Classifier: Operating System :: MacOS
Classifier: Operating System :: Microsoft :: Windows
Classifier: Operating System :: POSIX :: Linux
Classifier: Programming Language :: Python
Classifier: Programming Language :: Python :: 3
Classifier: Programming Language :: Python :: 3 :: Only
Classifier: Programming Language :: Python :: 3.9
Classifier: Programming Language :: Python :: 3.10
Classifier: Programming Language :: Python :: 3.11
Classifier: Programming Language :: Python :: 3.12
Classifier: Programming Language :: Python :: 3.13
Classifier: Topic :: Scientific/Engineering
Classifier: Topic :: Scientific/Engineering :: Mathematics
Classifier: Topic :: Scientific/Engineering :: Physics
Requires-Python: >=3.9
Requires-Dist: cvxopt
Requires-Dist: cygv
Requires-Dist: joblib
Requires-Dist: numpy
Requires-Dist: ortools
Requires-Dist: osqp
Requires-Dist: pplpy
Requires-Dist: pypalp
Requires-Dist: python-flint
Requires-Dist: qpsolvers
Requires-Dist: regfans
Requires-Dist: requests
Requires-Dist: scipy
Requires-Dist: tqdm
Requires-Dist: triangulumancer
Provides-Extra: mosek
Requires-Dist: mosek; extra == 'mosek'
Provides-Extra: test
Requires-Dist: pytest; extra == 'test'
